examples/__init__.py
examples/basic/__init__.py
examples/basic/app.py
flask_select2/__init__.py
flask_select2/_compat.py
flask_select2/select2.py
flask_select2/contrib/__init__.py
flask_select2/contrib/sqla/__init__.py
flask_select2/contrib/sqla/ajax.py
flask_select2/contrib/sqla/tools.py
flask_select2/form/__init__.py
flask_select2/form/fields.py
flask_select2/form/widgets.py
flask_select2/model/__init__.py
flask_select2/model/ajax.py
flask_select2/model/fields.py
flask_select2/model/widgets.py
flask_select2/static/js/form.js
flask_select2/static/vendor/select2/.gitignore
flask_select2/static/vendor/select2/CONTRIBUTING.md
flask_select2/static/vendor/select2/LICENSE
flask_select2/static/vendor/select2/README.md
flask_select2/static/vendor/select2/bower.json
flask_select2/static/vendor/select2/component.json
flask_select2/static/vendor/select2/composer.json
flask_select2/static/vendor/select2/package.json
flask_select2/static/vendor/select2/release.sh
flask_select2/static/vendor/select2/select2-bootstrap.css
flask_select2/static/vendor/select2/select2-bootstrap3.css
flask_select2/static/vendor/select2/select2-spinner.gif
flask_select2/static/vendor/select2/select2.css
flask_select2/static/vendor/select2/select2.jquery.json
flask_select2/static/vendor/select2/select2.js
flask_select2/static/vendor/select2/select2.min.js
flask_select2/static/vendor/select2/select2.png
flask_select2/static/vendor/select2/select2_locale_ar.js
flask_select2/static/vendor/select2/select2_locale_az.js
flask_select2/static/vendor/select2/select2_locale_bg.js
flask_select2/static/vendor/select2/select2_locale_ca.js
flask_select2/static/vendor/select2/select2_locale_cs.js
flask_select2/static/vendor/select2/select2_locale_da.js
flask_select2/static/vendor/select2/select2_locale_de.js
flask_select2/static/vendor/select2/select2_locale_el.js
flask_select2/static/vendor/select2/select2_locale_en.js.template
flask_select2/static/vendor/select2/select2_locale_es.js
Flask_Select2-0.1.dist-info/LICENSE
Flask_Select2-0.1.dist-info/METADATA
Flask_Select2-0.1.dist-info/WHEEL
Flask_Select2-0.1.dist-info/top_level.txt
Flask_Select2-0.1.dist-info/RECORD
