Metadata-Version: 2.1
Name: Flask-Select2
Version: 0.1
Summary: Flask integration with Select2.js
Home-page: https://github.com/pjcunningham/Flask-Select2
Author: Paul Cunningham
Author-email: pjcunningham@borsuk.co.uk
License: MIT License
Keywords: flask,select2
Platform: any
Classifier: Development Status :: 3 - Alpha
Classifier: Environment :: Web Environment
Classifier: Operating System :: OS Independent
Classifier: Topic :: Utilities
Classifier: Programming Language :: Python :: 2
Classifier: Programming Language :: Python :: 2.6
Classifier: Programming Language :: Python :: 2.7
Classifier: Programming Language :: Python :: 3
Classifier: Programming Language :: Python :: 3.3
Classifier: Programming Language :: Python :: 3.4
Classifier: Programming Language :: Python :: Implementation :: PyPy
Classifier: Topic :: Internet :: WWW/HTTP :: Dynamic Content
Classifier: Topic :: Software Development :: Libraries :: Python Modules
Classifier: License :: OSI Approved :: MIT License
Requires-Dist: Flask (>=0.7)
Requires-Dist: wtforms
